{
    "gui": {
        "editor_gaphas": {
            "name": {
                "rel_pos": {
                    "__jsonqualname__": "__builtin__.tuple", 
                    "items": [
                        1.4280663003919472, 
                        1.2814509848649323
                    ]
                }, 
                "size": {
                    "__jsonqualname__": "__builtin__.tuple", 
                    "items": [
                        11.320807546906654, 
                        5.809862328913585
                    ]
                }
            }, 
            "rel_pos": {
                "__jsonqualname__": "__builtin__.tuple", 
                "items": [
                    48.92684489033127, 
                    9.847191050004767
                ]
            }, 
            "size": {
                "__jsonqualname__": "__builtin__.tuple", 
                "items": [
                    15.506965374561375, 
                    16.599606654038812
                ]
            }
        }
    }, 
    "income": {
        "gui": {
            "editor_gaphas": {
                "rel_pos": {
                    "__jsonqualname__": "__builtin__.tuple", 
                    "items": [
                        0.3101393074912275, 
                        1.327968532323105
                    ]
                }
            }
        }
    }, 
    "outcome-1": {
        "gui": {
            "editor_gaphas": {
                "rel_pos": {
                    "__jsonqualname__": "__builtin__.tuple", 
                    "items": [
                        12.015622457440125, 
                        0.3101393074912275
                    ]
                }
            }
        }
    }, 
    "outcome-2": {
        "gui": {
            "editor_gaphas": {
                "rel_pos": {
                    "__jsonqualname__": "__builtin__.tuple", 
                    "items": [
                        12.015622457440125, 
                        0.3101393074912275
                    ]
                }
            }
        }
    }, 
    "outcome0": {
        "gui": {
            "editor_gaphas": {
                "rel_pos": {
                    "__jsonqualname__": "__builtin__.tuple", 
                    "items": [
                        15.196826067070148, 
                        1.327968532323105
                    ]
                }
            }
        }
    }, 
    "outcome1": {
        "gui": {
            "editor_gaphas": {
                "rel_pos": {
                    "__jsonqualname__": "__builtin__.tuple", 
                    "items": [
                        15.196826067070148, 
                        2.65593706464621
                    ]
                }
            }
        }
    }
}