{
    "gui": {
        "editor_gaphas": {
            "name": {
                "rel_pos": {
                    "__jsonqualname__": "__builtin__.tuple", 
                    "items": [
                        2.3881912610086147, 
                        3.6214028418644375
                    ]
                }, 
                "size": {
                    "__jsonqualname__": "__builtin__.tuple", 
                    "items": [
                        43.408470971675506, 
                        26.373228455288814
                    ]
                }
            }, 
            "rel_pos": {
                "__jsonqualname__": "__builtin__.tuple", 
                "items": [
                    3681.771061940254, 
                    132.43791351298933
                ]
            }, 
            "size": {
                "__jsonqualname__": "__builtin__.tuple", 
                "items": [
                    52.91642432119616, 
                    88.5622525061071
                ]
            }
        }
    }, 
    "income": {
        "gui": {
            "editor_gaphas": {
                "rel_pos": {
                    "__jsonqualname__": "__builtin__.tuple", 
                    "items": [
                        1.0583284864239233, 
                        6.028166504066015
                    ]
                }
            }
        }
    }, 
    "outcome-1": {
        "gui": {
            "editor_gaphas": {
                "rel_pos": {
                    "__jsonqualname__": "__builtin__.tuple", 
                    "items": [
                        39.93579329394146, 
                        1.0583284864239233
                    ]
                }
            }
        }
    }, 
    "outcome-2": {
        "gui": {
            "editor_gaphas": {
                "rel_pos": {
                    "__jsonqualname__": "__builtin__.tuple", 
                    "items": [
                        36.46311561620742, 
                        1.0583284864239233
                    ]
                }
            }
        }
    }, 
    "outcome0": {
        "gui": {
            "editor_gaphas": {
                "rel_pos": {
                    "__jsonqualname__": "__builtin__.tuple", 
                    "items": [
                        51.858095834772236, 
                        6.028166504066015
                    ]
                }
            }
        }
    }, 
    "output_data_port0": {
        "gui": {
            "editor_gaphas": {
                "rel_pos": {
                    "__jsonqualname__": "__builtin__.tuple", 
                    "items": [
                        51.858095834772236, 
                        69.32391479675917
                    ]
                }
            }
        }
    }, 
    "output_data_port1": {
        "gui": {
            "editor_gaphas": {
                "rel_pos": {
                    "__jsonqualname__": "__builtin__.tuple", 
                    "items": [
                        51.858095834772236, 
                        63.29574829269315
                    ]
                }
            }
        }
    }, 
    "output_data_port2": {
        "gui": {
            "editor_gaphas": {
                "rel_pos": {
                    "__jsonqualname__": "__builtin__.tuple", 
                    "items": [
                        51.858095834772236, 
                        57.267581788627155
                    ]
                }
            }
        }
    }, 
    "output_data_port3": {
        "gui": {
            "editor_gaphas": {
                "rel_pos": {
                    "__jsonqualname__": "__builtin__.tuple", 
                    "items": [
                        51.858095834772236, 
                        51.239415284561154
                    ]
                }
            }
        }
    }, 
    "output_data_port4": {
        "gui": {
            "editor_gaphas": {
                "rel_pos": {
                    "__jsonqualname__": "__builtin__.tuple", 
                    "items": [
                        51.858095834772236, 
                        45.21124878049512
                    ]
                }
            }
        }
    }
}