{
    "gui": {
        "editor_gaphas": {
            "name": {
                "rel_pos": {
                    "__jsonqualname__": "__builtin__.tuple", 
                    "items": [
                        2.9542325282427555, 
                        5.641979237785563
                    ]
                }, 
                "size": {
                    "__jsonqualname__": "__builtin__.tuple", 
                    "items": [
                        62.84483368277348, 
                        42.128672241992376
                    ]
                }
            }, 
            "rel_pos": {
                "__jsonqualname__": "__builtin__.tuple", 
                "items": [
                    2210.9721931162585, 
                    769.2278797451477
                ]
            }, 
            "size": {
                "__jsonqualname__": "__builtin__.tuple", 
                "items": [
                    69.76642830736245, 
                    129.43837879173344
                ]
            }
        }
    }, 
    "income": {
        "gui": {
            "editor_gaphas": {
                "rel_pos": {
                    "__jsonqualname__": "__builtin__.tuple", 
                    "items": [
                        1.395328566147249, 
                        9.629410798169685
                    ]
                }
            }
        }
    }, 
    "input_data_port0": {
        "gui": {
            "editor_gaphas": {
                "rel_pos": {
                    "__jsonqualname__": "__builtin__.tuple", 
                    "items": [
                        1.395328566147249, 
                        110.7382241789514
                    ]
                }
            }
        }
    }, 
    "input_data_port3": {
        "gui": {
            "editor_gaphas": {
                "rel_pos": {
                    "__jsonqualname__": "__builtin__.tuple", 
                    "items": [
                        1.395328566147249, 
                        101.10881338078171
                    ]
                }
            }
        }
    }, 
    "input_data_port5": {
        "gui": {
            "editor_gaphas": {
                "rel_pos": {
                    "__jsonqualname__": "__builtin__.tuple", 
                    "items": [
                        1.395328566147249, 
                        91.47940258261197
                    ]
                }
            }
        }
    }, 
    "input_data_port6": {
        "gui": {
            "editor_gaphas": {
                "rel_pos": {
                    "__jsonqualname__": "__builtin__.tuple", 
                    "items": [
                        1.395328566147249, 
                        81.84999178444234
                    ]
                }
            }
        }
    }, 
    "outcome-1": {
        "gui": {
            "editor_gaphas": {
                "rel_pos": {
                    "__jsonqualname__": "__builtin__.tuple", 
                    "items": [
                        59.68716890757945, 
                        1.395328566147249
                    ]
                }
            }
        }
    }, 
    "outcome-2": {
        "gui": {
            "editor_gaphas": {
                "rel_pos": {
                    "__jsonqualname__": "__builtin__.tuple", 
                    "items": [
                        54.496980306920385, 
                        1.395328566147249
                    ]
                }
            }
        }
    }, 
    "outcome0": {
        "gui": {
            "editor_gaphas": {
                "rel_pos": {
                    "__jsonqualname__": "__builtin__.tuple", 
                    "items": [
                        68.3710997412152, 
                        9.629410798169685
                    ]
                }
            }
        }
    }, 
    "outcome1": {
        "gui": {
            "editor_gaphas": {
                "rel_pos": {
                    "__jsonqualname__": "__builtin__.tuple", 
                    "items": [
                        68.3710997412152, 
                        19.25882159633937
                    ]
                }
            }
        }
    }, 
    "output_data_port1": {
        "gui": {
            "editor_gaphas": {
                "rel_pos": {
                    "__jsonqualname__": "__builtin__.tuple", 
                    "items": [
                        68.3710997412152, 
                        110.7382241789514
                    ]
                }
            }
        }
    }, 
    "output_data_port2": {
        "gui": {
            "editor_gaphas": {
                "rel_pos": {
                    "__jsonqualname__": "__builtin__.tuple", 
                    "items": [
                        68.3710997412152, 
                        101.10881338078171
                    ]
                }
            }
        }
    }
}